tksplash/__init__.py
tksplash/tksplash.py
tksplash-0.0.8.dist-info/LICENSE
tksplash-0.0.8.dist-info/METADATA
tksplash-0.0.8.dist-info/WHEEL
tksplash-0.0.8.dist-info/top_level.txt
tksplash-0.0.8.dist-info/RECORD
